spreadsheet_splitter/__init__.py
spreadsheet_splitter/splitter.py
spreadsheet_splitter-0.1.0.dist-info/METADATA
spreadsheet_splitter-0.1.0.dist-info/WHEEL
spreadsheet_splitter-0.1.0.dist-info/entry_points.txt
spreadsheet_splitter-0.1.0.dist-info/licenses/LICENSE
spreadsheet_splitter-0.1.0.dist-info/RECORD
