Metadata-Version: 2.4
Name: spreadsheet-splitter
Version: 0.1.0
Summary: A Python command-line tool to split large Excel (.xls or .xlsx) files into smaller parts with low memory usage.
Project-URL: Homepage, https://github.com/parsaloi/spreadsheet_splitter
Project-URL: Documentation, https://github.com/parsaloi/spreadsheet_splitter/tree/main/docs
Project-URL: Repository, https://github.com/parsaloi/spreadsheet_splitter
Project-URL: Issues, https://github.com/parsaloi/spreadsheet_splitter/issues
Author-email: Parsa Loi <parsa@example.com>
License: MIT
License-File: LICENSE
Keywords: excel,large-files,pandas,split,spreadsheet,xls,xlsx
Classifier: Development Status :: 4 - Beta
Classifier: Intended Audience :: Developers
Classifier: License :: OSI Approved :: MIT License
Classifier: Operating System :: OS Independent
Classifier: Programming Language :: Python :: 3
Classifier: Programming Language :: Python :: 3.13
Classifier: Topic :: Office/Business :: Office Suites
Classifier: Topic :: Utilities
Requires-Python: >=3.13
Requires-Dist: openpyxl>=3.1.5
Requires-Dist: pandas>=2.2.3
Requires-Dist: psutil>=7.0.0
Requires-Dist: pyexcelerate>=0.13.0
Requires-Dist: xlrd>=2.0.1
Requires-Dist: xlwt>=1.3.0
